example/ex1.v
module ex1(x1,x2,x3,f);
    input x1, x2, x3;
    output f;
    assign f = (x1 & x2) | (~x2 & x3);
endmodule

example/ex1tb.v
`timescale 1ns/1ns
`include "ex1.v"

module ex1tb();
reg x1,x2,x3;
wire f;

ex1 ex(x1,x2,x3,f);
initial 
begin
    
    $dumpfile("ex1tb.vcd");
    $dumpvars(0,ex1tb);

    x1=1'b0; x2=1'b0; x3=1'b0;
    #20;

    x1=1'b0; x2=1'b0; x3=1'b1;
    #20;

    x1=1'b0; x2=1'b1; x3=1'b0;
    #20;

    x1=1'b0; x2=1'b1; x3=1'b1;
    #20;

    x1=1'b1; x2=1'b0; x3=1'b0;
    #20;

    x1=1'b1; x2=1'b0; x3=1'b1;
    #20;

    x1=1'b1; x2=1'b1; x3=1'b0;
    #20;

    x1=1'b1; x2=1'b1; x3=1'b1;
    #20;

    $display("Test complete");

end

endmodule

example/ex1tb.vcd
$date
	Wed Aug 31 22:29:43 2022
$end
$version
	Icarus Verilog
$end
$timescale
	1ns
$end
$scope module ex1tb $end
$var wire 1 ! f $end
$var reg 1 " x1 $end
$var reg 1 # x2 $end
$var reg 1 $ x3 $end
$scope module ex $end
$var wire 1 ! f $end
$var wire 1 " x1 $end
$var wire 1 # x2 $end
$var wire 1 $ x3 $end
$upscope $end
$upscope $end
$enddefinitions $end
#0
$dumpvars
0$
0#
0"
0!
$end
#20
1!
1$
#40
0!
0$
1#
#60
1$
#80
0$
0#
1"
#100
1!
1$
#120
0$
1#
#140
1$
