Lab1/Question1.v
module Question1(a,b,c,d,f);
    input a,b,c,d;
    output f;

    and(g,a,b);
    or(h,g,c);
    not(i,h);
    and(j,i,d);

    and(g1,a,b);
    or(h1,c,g1);
    or(i1,d,h1);

    and(f,i1,j);
endmodule

Lab1/Qa_tb.v
`timescale 1ns/1ns
`include "Question1.v"

module Qa_tb();
reg a,b,c,d;
wire f;

Question1 Q1(a,b,c,d,f);
initial
begin

    $dumpfile("Qa_1tb.vcd");
    $dumpvars(0,Qa_tb);

     
    a=1'b0; b=1'b0; c=1'b0; d=1'b0;
    #20;
    
    a=1'b0; b=1'b0; c=1'b0; d=1'b1;
    #20;
    
    a=1'b0; b=1'b0; c=1'b1; d=1'b0;
    #20;
    
    a=1'b0; b=1'b0; c=1'b1; d=1'b1;
    #20;
    
    a=1'b0; b=1'b1; c=1'b0; d=1'b0;
    #20;
    
    a=1'b0; b=1'b1; c=1'b0; d=1'b1;
    #20;
    
    a=1'b0; b=1'b1; c=1'b1; d=1'b0;
    #20;
    
    a=1'b0; b=1'b1; c=1'b1; d=1'b1;
    #20;
    
    a=1'b1; b=1'b0; c=1'b0; d=1'b0;
    #20;
    
    a=1'b1; b=1'b0; c=1'b0; d=1'b1;
    #20;
    
    a=1'b1; b=1'b0; c=1'b1; d=1'b0;
    #20;
    
    a=1'b1; b=1'b0; c=1'b1; d=1'b1;
    #20;
    
    a=1'b1; b=1'b1; c=1'b0; d=1'b0;
    #20;
    
    a=1'b1; b=1'b1; c=1'b0; d=1'b1;
    #20;
    
    a=1'b1; b=1'b1; c=1'b1; d=1'b0;
    #20;
    
    a=1'b1; b=1'b1; c=1'b1; d=1'b1;
    #20;


    $display("Test complete");

end

endmodule

DSD/Lab1/Qa_1tb.vcd
$date
	Wed Aug 31 22:50:15 2022
$end
$version
	Icarus Verilog
$end
$timescale
	1ns
$end
$scope module Qa_tb $end
$var wire 1 ! f $end
$var reg 1 " a $end
$var reg 1 # b $end
$var reg 1 $ c $end
$var reg 1 % d $end
$scope module Q1 $end
$var wire 1 " a $end
$var wire 1 # b $end
$var wire 1 $ c $end
$var wire 1 % d $end
$var wire 1 ! f $end
$var wire 1 & g $end
$var wire 1 ' g1 $end
$var wire 1 ( h $end
$var wire 1 ) h1 $end
$var wire 1 * i $end
$var wire 1 + i1 $end
$var wire 1 , j $end
$upscope $end
$upscope $end
$enddefinitions $end
#0
$dumpvars
0,
0+
1*
0)
0(
0'
0&
0%
0$
0#
0"
0!
$end
#20
1!
1,
1+
1%
#40
0!
0*
0,
1(
1)
0%
1$
#60
1%
#80
1*
0+
0(
0)
0%
0$
1#
#100
1!
1,
1+
1%
#120
0!
0*
0,
1(
1)
0%
1$
#140
1%
#160
1*
0+
0(
0)
0%
0$
0#
1"
#180
1!
1,
1+
1%
#200
0!
0*
0,
1(
1)
0%
1$
#220
1%
#240
1&
1'
0%
0$
1#
#260
1%
#280
0%
1$
#300
1%
