Lab1/Q1.v
module Q1 (x1,x2,x3,f);
    input x1,x2,x3;
    output f;
    assign f = (x1 & x2) | (x2 & x3);
endmodule

Lab2/Q1_tb.v
`timescale 1ns/1ns
`include "Q1.v"

module Q1_tb();
reg  x1, x2, x3;
wire f;

Q1 ex(x1, x2, x3, f);
initial
begin
        $dumpfile("Q1_tb.vcd");
        $dumpvars(0,Q1_tb);

        x1=1'b0; x2 = 1'b0; x3=1'b0;
        #20;

        x1=1'b0; x2 = 1'b0; x3=1'b1;
        #20;

        x1=1'b0; x2 = 1'b1; x3=1'b0;
        #20;

        x1=1'b0; x2 = 1'b1; x3=1'b1;
        #20;

        x1=1'b1; x2 = 1'b0; x3=1'b0;
        #20;

        x1=1'b1; x2 = 1'b0; x3=1'b1;
        #20;

        x1=1'b1; x2 = 1'b1; x3=1'b0;
        #20;

        x1=1'b1; x2 = 1'b1; x3=1'b1;
        #20;
        

        $display("Test complete");

end

endmodule

Lab2/Q1_tb.vcd
$date
	Wed Oct 12 18:53:12 2022
$end
$version
	Icarus Verilog
$end
$timescale
	1ns
$end
$scope module Q1_tb $end
$var wire 1 ! f $end
$var reg 1 " x1 $end
$var reg 1 # x2 $end
$var reg 1 $ x3 $end
$scope module ex $end
$var wire 1 ! f $end
$var wire 1 " x1 $end
$var wire 1 # x2 $end
$var wire 1 $ x3 $end
$upscope $end
$upscope $end
$enddefinitions $end
#0
$dumpvars
0$
0#
0"
0!
$end
#20
1$
#40
0$
1#
#60
1!
1$
#80
0!
0$
0#
1"
#100
1$
#120
1!
0$
1#
#140
1$
