Lab2/Q2.v
module Q2 ( x1, x2, x3,x4,f,g);
  input x1,x2,x3,x4;
  output f,g;
  assign f = ((~(x1&x2))^x3^x4);
  assign g = (~(x3|x2|x4));
endmodule

Lab2/Q2_tb.v
`timescale 1ns/1ns
`include "Q2.v"

module Q2_tb();
  reg  a, b, c, d;
  wire f,g;

  Q2 ex(a, b, c, d, f, g);
  initial
  begin
    $dumpfile("Q2_tb.vcd");
    $dumpvars(0,Q2_tb);

	a=1'b0; b=1'b0; c=1'b0; d=1'b0;
	#20;
	
	a=1'b0; b=1'b0; c=1'b0; d=1'b1;
	#20;
	
	a=1'b0; b=1'b0; c=1'b1; d=1'b0;
	#20;
	
	a=1'b0; b=1'b0; c=1'b1; d=1'b1;
	#20;
	
	a=1'b0; b=1'b1; c=1'b0; d=1'b0;
	#20;
	
	a=1'b0; b=1'b1; c=1'b0; d=1'b1;
	#20;
	
	a=1'b0; b=1'b1; c=1'b1; d=1'b0;
	#20;
	
	a=1'b0; b=1'b1; c=1'b1; d=1'b1;
	#20;
	
	a=1'b1; b=1'b0; c=1'b0; d=1'b0;
	#20;
	
	a=1'b1; b=1'b0; c=1'b0; d=1'b1;
	#20;
	
	a=1'b1; b=1'b0; c=1'b1; d=1'b0;
	#20;
	
	a=1'b1; b=1'b0; c=1'b1; d=1'b1;
	#20;
	
	a=1'b1; b=1'b1; c=1'b0; d=1'b0;
	#20;
	
	a=1'b1; b=1'b1; c=1'b0; d=1'b1;
	#20;
	
	a=1'b1; b=1'b1; c=1'b1; d=1'b0;
	#20;
	
	a=1'b1; b=1'b1; c=1'b1; d=1'b1;
	#20;


    $display("Test complete");

  end

endmodule

Lab2/Q2_tb.vcd
$date
	Wed Oct 12 21:41:28 2022
$end
$version
	Icarus Verilog
$end
$timescale
	1ns
$end
$scope module Q2_tb $end
$var wire 1 ! g $end
$var wire 1 " f $end
$var reg 1 # a $end
$var reg 1 $ b $end
$var reg 1 % c $end
$var reg 1 & d $end
$scope module ex $end
$var wire 1 " f $end
$var wire 1 ! g $end
$var wire 1 # x1 $end
$var wire 1 $ x2 $end
$var wire 1 % x3 $end
$var wire 1 & x4 $end
$upscope $end
$upscope $end
$enddefinitions $end
#0
$dumpvars
0&
0%
0$
0#
1"
1!
$end
#20
0!
0"
1&
#40
0&
1%
#60
1"
1&
#80
0&
0%
1$
#100
0"
1&
#120
0&
1%
#140
1"
1&
#160
1!
0&
0%
0$
1#
#180
0!
0"
1&
#200
0&
1%
#220
1"
1&
#240
0"
0&
0%
1$
#260
1"
1&
#280
0&
1%
#300
0"
1&
