Lab3/Q1.v
module Q1 (a,b,c,d,f);
    input a,b,c,d;
    output f;
    assign f = ((c & d)|(b & ~c & ~d)|(~a & b)|(~b & c));
endmodule

Lab3/Q1_tb.v
`timescale 1ns/1ns
`include "Q1.v"

module Q1_tb();
    reg a,b,c,d;
    wire f;

    Q1 ex(a,b,c,d,f);
    initial
    begin
        $dumpfile("Q1_tb.vcd");
        $dumpvars(0,Q1_tb);

        a=1'b0; b=1'b0; c=1'b0; d=1'b0;
        #20;
        
        a=1'b0; b=1'b0; c=1'b0; d=1'b1;
        #20;
        
        a=1'b0; b=1'b0; c=1'b1; d=1'b0;
        #20;
        
        a=1'b0; b=1'b0; c=1'b1; d=1'b1;
        #20;
        
        a=1'b0; b=1'b1; c=1'b0; d=1'b0;
        #20;
        
        a=1'b0; b=1'b1; c=1'b0; d=1'b1;
        #20;
        
        a=1'b0; b=1'b1; c=1'b1; d=1'b0;
        #20;
        
        a=1'b0; b=1'b1; c=1'b1; d=1'b1;
        #20;
        
        a=1'b1; b=1'b0; c=1'b0; d=1'b0;
        #20;
        
        a=1'b1; b=1'b0; c=1'b0; d=1'b1;
        #20;
        
        a=1'b1; b=1'b0; c=1'b1; d=1'b0;
        #20;
        
        a=1'b1; b=1'b0; c=1'b1; d=1'b1;
        #20;
        
        a=1'b1; b=1'b1; c=1'b0; d=1'b0;
        #20;
        
        a=1'b1; b=1'b1; c=1'b0; d=1'b1;
        #20;
        
        a=1'b1; b=1'b1; c=1'b1; d=1'b0;
        #20;
        
        a=1'b1; b=1'b1; c=1'b1; d=1'b1;
        #20;
    
        $display("okk okk");
        

    end
endmodule

Lab3/Q1_tb.vcd
$date
	Thu Oct 13 00:14:36 2022
$end
$version
	Icarus Verilog
$end
$timescale
	1ns
$end
$scope module Q1_tb $end
$var wire 1 ! f $end
$var reg 1 " a $end
$var reg 1 # b $end
$var reg 1 $ c $end
$var reg 1 % d $end
$scope module ex $end
$var wire 1 " a $end
$var wire 1 # b $end
$var wire 1 $ c $end
$var wire 1 % d $end
$var wire 1 ! f $end
$upscope $end
$upscope $end
$enddefinitions $end
#0
$dumpvars
0%
0$
0#
0"
0!
$end
#20
1%
#40
1!
0%
1$
#60
1%
#80
0%
0$
1#
#100
1%
#120
0%
1$
#140
1%
#160
0!
0%
0$
0#
1"
#180
1%
#200
1!
0%
1$
#220
1%
#240
1!
0%
0$
1#
#260
0!
1%
#280
0%
1$
#300
1!
1%
