Lab3/Q3.v
module Q3(a,b,c,d,f);
    input a,b,c,d;
    output f;
    assign f = ((b | c)&(~b | c)); 
endmodule

Lab3/Q3_tb.v
`timescale 1ns/1ns
`include "Q3.v"
module Q3_tb();
  reg a,b,c,d;
  wire f;

  Q3 ex(a,b,c,d,f);
  initial
  begin
    $dumpfile("Q3_tb.vcd");
    $dumpvars(0,Q3_tb);

    a=1'b0;
    b=1'b0;
    c=1'b0;
    d=1'b0;
    #20;

    a=1'b0;
    b=1'b0;
    c=1'b0;
    d=1'b1;
    #20;

    a=1'b0;
    b=1'b0;
    c=1'b1;
    d=1'b0;
    #20;

    a=1'b0;
    b=1'b0;
    c=1'b1;
    d=1'b1;
    #20;

    a=1'b0;
    b=1'b1;
    c=1'b0;
    d=1'b0;
    #20;

    a=1'b0;
    b=1'b1;
    c=1'b0;
    d=1'b1;
    #20;

    a=1'b0;
    b=1'b1;
    c=1'b1;
    d=1'b0;
    #20;

    a=1'b0;
    b=1'b1;
    c=1'b1;
    d=1'b1;
    #20;

    a=1'b1;
    b=1'b0;
    c=1'b0;
    d=1'b0;
    #20;

    a=1'b1;
    b=1'b0;
    c=1'b0;
    d=1'b1;
    #20;

    a=1'b1;
    b=1'b0;
    c=1'b1;
    d=1'b0;
    #20;

    a=1'b1;
    b=1'b0;
    c=1'b1;
    d=1'b1;
    #20;

    a=1'b1;
    b=1'b1;
    c=1'b0;
    d=1'b0;
    #20;

    a=1'b1;
    b=1'b1;
    c=1'b0;
    d=1'b1;
    #20;

    a=1'b1;
    b=1'b1;
    c=1'b1;
    d=1'b0;
    #20;

    a=1'b1;
    b=1'b1;
    c=1'b1;
    d=1'b1;
    #20;

    $display("okk okk");

  end
endmodule

Lab3/Q3_tb.vcd
$date
	Thu Oct 13 02:03:21 2022
$end
$version
	Icarus Verilog
$end
$timescale
	1ns
$end
$scope module Q3_tb $end
$var wire 1 ! f $end
$var reg 1 " a $end
$var reg 1 # b $end
$var reg 1 $ c $end
$var reg 1 % d $end
$scope module ex $end
$var wire 1 " a $end
$var wire 1 # b $end
$var wire 1 $ c $end
$var wire 1 % d $end
$var wire 1 ! f $end
$upscope $end
$upscope $end
$enddefinitions $end
#0
$dumpvars
0%
0$
0#
0"
0!
$end
#20
1%
#40
1!
0%
1$
#60
1%
#80
0!
0%
0$
1#
#100
1%
#120
1!
0%
1$
#140
1%
#160
0!
0%
0$
0#
1"
#180
1%
#200
1!
0%
1$
#220
1%
#240
0!
0%
0$
1#
#260
1%
#280
1!
0%
1$
#300
1%
